make_spirals/__init__.py
make_spirals/make_spirals.py
make_spirals-0.2.dist-info/licenses/LICENSE.txt
make_spirals-0.2.dist-info/METADATA
make_spirals-0.2.dist-info/WHEEL
make_spirals-0.2.dist-info/top_level.txt
make_spirals-0.2.dist-info/RECORD
