Metadata-Version: 2.4
Name: make_spirals
Version: 0.2
Summary: make_spirals generates a synthetic data set composed of interlaced Archimedean spirals.
Home-page: https://github.com/KNODIS-Research-Group/make_spirals
Download-URL: https://github.com/KNODIS-Research-Group/make_spirals/archive/v0_1.tar.gz
Author: Fernando Ortega
Author-email: fernando.ortega@upm.es
License: apache-2.0
Keywords: scikit-learn,supervised-learning,classification,dataset,spirals
Classifier: Development Status :: 4 - Beta
Classifier: Intended Audience :: Developers
Classifier: Topic :: Software Development :: Build Tools
Classifier: License :: OSI Approved :: Apache Software License
Classifier: Programming Language :: Python :: 3
Classifier: Programming Language :: Python :: 3.4
Classifier: Programming Language :: Python :: 3.5
Classifier: Programming Language :: Python :: 3.6
License-File: LICENSE.txt
Requires-Dist: numpy
Requires-Dist: scikit-learn
Dynamic: author
Dynamic: author-email
Dynamic: classifier
Dynamic: download-url
Dynamic: home-page
Dynamic: keywords
Dynamic: license
Dynamic: license-file
Dynamic: requires-dist
Dynamic: summary
